{"nodes": [{"id": "d_projects_sports_tv_backend_tests_test_scrapers_py", "label": "test_scrapers.py", "file_type": "code", "source_file": "D:\\projects\\sports_tv\\backend\\tests\\test_scrapers.py", "source_location": "L1"}, {"id": "tests_test_scrapers_test_extract_invalid_url", "label": "test_extract_invalid_url()", "file_type": "code", "source_file": "D:\\projects\\sports_tv\\backend\\tests\\test_scrapers.py", "source_location": "L5"}], "edges": [{"source": "d_projects_sports_tv_backend_tests_test_scrapers_py", "target": "pytest", "relation": "imports", "context": "import", "confidence": "EXTRACTED", "source_file": "D:\\projects\\sports_tv\\backend\\tests\\test_scrapers.py", "source_location": "L1", "weight": 1.0}, {"source": "d_projects_sports_tv_backend_tests_test_scrapers_py", "target": "scrapers", "relation": "imports_from", "context": "import", "confidence": "EXTRACTED", "source_file": "D:\\projects\\sports_tv\\backend\\tests\\test_scrapers.py", "source_location": "L2", "weight": 1.0}, {"source": "d_projects_sports_tv_backend_tests_test_scrapers_py", "target": "tests_test_scrapers_test_extract_invalid_url", "relation": "contains", "confidence": "EXTRACTED", "source_file": "D:\\projects\\sports_tv\\backend\\tests\\test_scrapers.py", "source_location": "L5", "weight": 1.0}], "raw_calls": [{"caller_nid": "tests_test_scrapers_test_extract_invalid_url", "callee": "extract_async", "is_member_call": false, "source_file": "D:\\projects\\sports_tv\\backend\\tests\\test_scrapers.py", "source_location": "L6"}, {"caller_nid": "tests_test_scrapers_test_extract_invalid_url", "callee": "isinstance", "is_member_call": false, "source_file": "D:\\projects\\sports_tv\\backend\\tests\\test_scrapers.py", "source_location": "L7"}, {"caller_nid": "tests_test_scrapers_test_extract_invalid_url", "callee": "startswith", "is_member_call": true, "source_file": "D:\\projects\\sports_tv\\backend\\tests\\test_scrapers.py", "source_location": "L8"}]}